ragagent_client/__init__.py
ragagent_client/api_client.py
ragagent_client/api_response.py
ragagent_client/configuration.py
ragagent_client/exceptions.py
ragagent_client/py.typed
ragagent_client/rest.py
ragagent_client/api/__init__.py
ragagent_client/api/agent_api.py
ragagent_client/api/cic_api.py
ragagent_client/api/health_api.py
ragagent_client/api/mcp_api.py
ragagent_client/api/mcp_api_api.py
ragagent_client/api/root_api.py
ragagent_client/api/ui_events_api.py
ragagent_client/api/waba_signup_api.py
ragagent_client/api/whats_app_api.py
ragagent_client/api/whatsapp0_api.py
ragagent_client/api/whatsapp_flow_api.py
ragagent_client/api/whatsapp_flows_api.py
ragagent_client/models/__init__.py
ragagent_client/models/abandoned_signup_data.py
ragagent_client/models/api_response.py
ragagent_client/models/error_signup_data.py
ragagent_client/models/http_validation_error.py
ragagent_client/models/ragagent_models_flow_webhook_encrypted_flow_data.py
ragagent_client/models/ragagent_ragatanga_flows_flow_webhook_handler_encrypted_flow_data.py
ragagent_client/models/signup_data.py
ragagent_client/models/successful_signup_data.py
ragagent_client/models/tool_execution_request.py
ragagent_client/models/ui_event_payload.py
ragagent_client/models/ui_event_request.py
ragagent_client/models/ui_event_response.py
ragagent_client/models/validation_error.py
ragagent_client/models/validation_error_loc_inner.py
ragagent_client/models/waba_signup_complete_request.py
ragagent_client/models/waba_signup_complete_response.py
ragagent_client/models/waba_signup_session_request.py
ragagent_client/models/waba_signup_session_response.py
ragagent_client/models/waba_token_exchange_request.py
ragagent_client/models/waba_token_exchange_response.py
ragagent_client-1.0.0.dist-info/METADATA
ragagent_client-1.0.0.dist-info/WHEEL
ragagent_client-1.0.0.dist-info/top_level.txt
ragagent_client-1.0.0.dist-info/RECORD
